CODCQC/CODCQC_main.py
CODCQC/__init__.py
CODCQC/qc_T_models/__init__.py
CODCQC/qc_T_models/aqc_check1.py
CODCQC/qc_T_models/aqc_check10.py
CODCQC/qc_T_models/aqc_check11.py
CODCQC/qc_T_models/aqc_check12.py
CODCQC/qc_T_models/aqc_check13.py
CODCQC/qc_T_models/aqc_check14.py
CODCQC/qc_T_models/aqc_check2.py
CODCQC/qc_T_models/aqc_check3.py
CODCQC/qc_T_models/aqc_check4.py
CODCQC/qc_T_models/aqc_check5.py
CODCQC/qc_T_models/aqc_check6.py
CODCQC/qc_T_models/aqc_check7.py
CODCQC/qc_T_models/aqc_check8.py
CODCQC/qc_T_models/aqc_check9.py
CODCQC/tests/Example1_single_cast_AutoQC.py
CODCQC/tests/Example2_WOD18_netCDF.py
CODCQC/tests/Example3_txt_AutoQC.py
CODCQC/tests/Example3_txt_input.txt
CODCQC/tests/Example4_mat.py
CODCQC/tests/__init__.py
CODCQC/tests/WOD18_mat_temp_data/CAS_T_S_1961_1.mat
CODCQC/tests/WOD18_mat_temp_data/CODCQCflag_CAS_T_S_1961_1.mat
CODCQC/tests/WOD18_netCDF_temp_data/CASv1_T_S_19400101_00001_BOT.nc
CODCQC/tests/WOD18_netCDF_temp_data/CASv1_T_S_19400101_00002_BOT.nc
CODCQC/tests/WOD18_netCDF_temp_data/CASv1_T_S_19400101_00003_BOT.nc
CODCQC/tests/WOD18_netCDF_temp_data/CASv1_T_S_19400101_00004_BOT.nc
CODCQC/tests/WOD18_netCDF_temp_data/CASv1_T_S_19400102_00001_BOT.nc
CODCQC/tests/WOD18_netCDF_temp_data/CASv1_T_S_19400102_00005_BOT.nc
CODCQC/tests/WOD18_netCDF_temp_data/CASv1_T_S_19400103_00001_BOT.nc
CODCQC/tests/WOD18_netCDF_temp_data/CASv1_T_S_19400103_00002_BOT.nc
CODCQC/tests/WOD18_netCDF_temp_data/CASv1_T_S_19400103_00005_BOT.nc
CODCQC/tests/WOD18_netCDF_temp_data/CASv1_T_S_19400104_00001_BOT.nc
CODCQC/tests/WOD18_netCDF_temp_data/CASv1_T_S_19400104_00002_BOT.nc
CODCQC/tests/WOD18_netCDF_temp_data/CASv1_T_S_19400104_00007_BOT.nc
CODCQC/tests/WOD18_netCDF_temp_data/CASv1_T_S_19400105_00001_BOT.nc
CODCQC/tests/WOD18_netCDF_temp_data/CASv1_T_S_19400105_00002_BOT.nc
CODCQC/tests/WOD18_netCDF_temp_data/CASv1_T_S_19400105_00003_BOT.nc
CODCQC/tests/WOD18_netCDF_temp_data/CASv1_T_S_19400105_00004_BOT.nc
CODCQC-1.0.dist-info/LICENSE
CODCQC-1.0.dist-info/METADATA
CODCQC-1.0.dist-info/WHEEL
CODCQC-1.0.dist-info/top_level.txt
CODCQC-1.0.dist-info/RECORD
