Metadata-Version: 2.1
Name: CODCQC
Version: 1.0
Summary: A climatology-based quality control algorithms for ocean temperature in-situ observations (Tan et al., 2023)
Home-page: https://github.com/zqtzt/CODCQC/
Author: Zhetao Tan; Lijing Cheng
Author-email: tanzhetao@mail.iap.ac.cn
Classifier: Programming Language :: Python :: 3
Classifier: License :: OSI Approved :: Apache Software License
Classifier: Operating System :: OS Independent
Requires-Python: >=3.7
License-File: LICENSE
Requires-Dist: numpy (>=1.20.1)
Requires-Dist: gsw (>=3.0.3)
Requires-Dist: scipy (>=1.5.2)
Requires-Dist: netCDF4 (>=1.5.4)
Requires-Dist: h5py (>=2.10.0)
